opennem/__init__.py
opennem-10.0.0.dist-info/METADATA
opennem-10.0.0.dist-info/WHEEL
opennem-10.0.0.dist-info/licenses/LICENSE
opennem-10.0.0.dist-info/RECORD
