Metadata-Version: 2.4
Name: opennem
Version: 10.0.0
Summary: OpenNEM Energy Market Data Access (DEPRECATED)
Project-URL: Homepage, https://github.com/opennem/opennem
Project-URL: Documentation, https://docs.openelectricity.org.au
Project-URL: Repository, https://github.com/opennem/opennem
Author-email: OpenNEM <enquiries@openelectricity.org.au>
License: MIT License
License-File: LICENSE
Classifier: Development Status :: 7 - Inactive
Classifier: License :: OSI Approved :: MIT License
Classifier: Operating System :: OS Independent
Classifier: Programming Language :: Python :: 3
Classifier: Programming Language :: Python :: 3.7
Classifier: Programming Language :: Python :: 3.8
Classifier: Programming Language :: Python :: 3.9
Classifier: Programming Language :: Python :: 3.10
Classifier: Programming Language :: Python :: 3.11
Requires-Python: >=3.7
